[
  {
    "full_name": "actions/checkout",
    "stargazers_count": 3096,
    "open_issues_count": 321,
    "forks_count": 1005
  },
  {
    "full_name": "irongut/CodeCoverageSummary",
    "stargazers_count": 64,
    "open_issues_count": 13,
    "forks_count": 20
  },
  {
    "full_name": "matlab-actions/run-tests",
    "stargazers_count": 28,
    "open_issues_count": 0,
    "forks_count": 12
  },
  {
    "full_name": "matlab-actions/setup-matlab",
    "stargazers_count": 51,
    "open_issues_count": 9,
    "forks_count": 14
  },
  {
    "full_name": "mathworks/climatedatastore",
    "stargazers_count": 9,
    "open_issues_count": 3,
    "forks_count": 2
  }
]